CHANGES.rst
MANIFEST.in
README.rst
setup.py
js/__init__.py
js.uploadify.egg-info/PKG-INFO
js.uploadify.egg-info/SOURCES.txt
js.uploadify.egg-info/dependency_links.txt
js.uploadify.egg-info/entry_points.txt
js.uploadify.egg-info/namespace_packages.txt
js.uploadify.egg-info/not-zip-safe
js.uploadify.egg-info/requires.txt
js.uploadify.egg-info/top_level.txt
js/uploadify/__init__.py
js/uploadify/test_uploadify.txt
js/uploadify/resources/jquery.uploadify.js
js/uploadify/resources/jquery.uploadify.min.js
js/uploadify/resources/uploadify-cancel.png
js/uploadify/resources/uploadify.css
js/uploadify/resources/uploadify.swf