Metadata-Version: 1.0
Name: js.uploadify
Version: 3.2.1
Summary: Fanstatic packaging of uploadify.js.
Home-page: https://github.com/tmassman/js.uploadify
Author: Thomas Massmann
Author-email: thomas.massmann@it-spir.it
License: BSD
Download-URL: http://pypi.python.org/pypi/js.uploadify
Platform: UNKNOWN
